geomesa_pyspark/__init__.py
geomesa_pyspark/types.py
pyrasterframes/__init__.py
pyrasterframes/rasterfunctions.py
pyrasterframes/rf_context.py
pyrasterframes/rf_ipython.py
pyrasterframes/rf_types.py
pyrasterframes/utils.py
pyrasterframes/version.py
pyrasterframes-0.11.1.dist-info/LICENSE
pyrasterframes-0.11.1.dist-info/METADATA
pyrasterframes-0.11.1.dist-info/WHEEL
pyrasterframes-0.11.1.dist-info/RECORD
