Metadata-Version: 2.1
Name: pyrasterframes
Version: 0.11.1
Summary: Access and process geospatial raster data in PySpark DataFrames
Home-page: https://rasterframes.io
License: Apache-2.0
Author: Astraea, Inc.
Author-email: info@astraea.earth
Requires-Python: >=3.8,<4
Classifier: Development Status :: 4 - Beta
Classifier: Environment :: Other Environment
Classifier: License :: OSI Approved :: Apache Software License
Classifier: Natural Language :: English
Classifier: Operating System :: Unix
Classifier: Programming Language :: Python :: 3
Classifier: Programming Language :: Python :: 3.8
Classifier: Programming Language :: Python :: 3.9
Classifier: Programming Language :: Python :: 3.10
Classifier: Programming Language :: Python :: 3.11
Classifier: Programming Language :: Python :: 3
Classifier: Topic :: Multimedia :: Graphics :: Graphics Conversion
Classifier: Topic :: Scientific/Engineering :: GIS
Classifier: Topic :: Software Development :: Libraries
Requires-Dist: deprecation (>=2.1.0,<3.0.0)
Requires-Dist: matplotlib (>=3.6.3,<4.0.0)
Requires-Dist: numpy (<1.23.0)
Requires-Dist: pandas (>=1.4.0,<2.0.0)
Requires-Dist: py4j (>=0.10.9.3,<0.11.0.0)
Requires-Dist: pyproj (>=3.4.1,<3.5.0)
Requires-Dist: pyspark (==3.3.2)
Requires-Dist: shapely (>=2.0.0,<3.0.0)
